CHANGELOG.rst
LICENSE
MANIFEST.in
README.rst
setup.cfg
setup.py
examples/djanguard/__init__.py
examples/djanguard/models.py
examples/djanguard/settings.py
examples/djanguard/urls.py
examples/djanguard/views.py
examples/djanguard/wsgi.py
examples/flask_sqla/__init__.py
examples/flask_sqla/app.py
examples/flask_sqla/fixtures.py
examples/flask_sqla/main.py
examples/flask_sqla/models.py
examples/flask_sqla/permissions.py
guardrail/__init__.py
guardrail.egg-info/PKG-INFO
guardrail.egg-info/SOURCES.txt
guardrail.egg-info/dependency_links.txt
guardrail.egg-info/requires.txt
guardrail.egg-info/top_level.txt
guardrail/core/__init__.py
guardrail/core/decorators.py
guardrail/core/exceptions.py
guardrail/core/models.py
guardrail/core/registry.py
guardrail/ext/__init__.py
guardrail/ext/peewee.py
guardrail/ext/pony.py
guardrail/ext/sqlalchemy.py
guardrail/ext/django/__init__.py
guardrail/ext/django/backends.py
guardrail/ext/django/models.py