Metadata-Version: 1.1
Name: guardrail
Version: 0.1.1
Summary: An extensible library for managing object-level permissions with support for SQLAlchemy, Peewee, Pony, and Django.
Home-page: https://github.com/jmcarp/guardrail
Author: Joshua Carp
Author-email: jm.carp@gmail.com
License: Copyright (c) 2015 Joshua Carp
